automagic_rest/__init__.py
automagic_rest/_version.py
automagic_rest/apps.py
automagic_rest/pagination.py
automagic_rest/settings.py
automagic_rest/views.py
automagic_rest/management/__init__.py
automagic_rest/management/commands/__init__.py
automagic_rest/management/commands/build_data_models.py
automagic_rest/templates/automagic_rest/models.html
automagic_rest/templates/automagic_rest/urls.html
automagic_rest-2.2.0.dist-info/licenses/LICENSE
automagic_rest-2.2.0.dist-info/METADATA
automagic_rest-2.2.0.dist-info/WHEEL
automagic_rest-2.2.0.dist-info/top_level.txt
automagic_rest-2.2.0.dist-info/RECORD
