Metadata-Version: 2.4
Name: automagic-rest
Version: 2.2.0
Summary: Automagic REST: Django REST Framework Code Generator for Underlying PostgreSQL DBs
Author-email: Tim Allen <flipper@peregrinesalon.com>
License: BSD-3-Clause
Project-URL: Homepage, https://github.com/wharton/automagic-rest
Project-URL: Repository, https://github.com/wharton/automagic-rest
Project-URL: Documentation, https://github.com/wharton/automagic-rest
Keywords: django,automagic-rest,rest,drf,django-rest-framework,djangorestframework
Classifier: Development Status :: 5 - Production/Stable
Classifier: Environment :: Web Environment
Classifier: Intended Audience :: Developers
Classifier: License :: OSI Approved :: BSD License
Classifier: Operating System :: OS Independent
Classifier: Programming Language :: Python :: 3
Classifier: Programming Language :: Python :: 3.7
Classifier: Programming Language :: Python :: 3.8
Classifier: Programming Language :: Python :: 3.9
Classifier: Programming Language :: Python :: 3.10
Classifier: Programming Language :: Python :: 3.11
Classifier: Programming Language :: Python :: 3.12
Classifier: Framework :: Django
Classifier: Framework :: Django :: 4
Classifier: Topic :: Internet :: WWW/HTTP
Classifier: Topic :: Internet :: WWW/HTTP :: Dynamic Content
Requires-Python: >=3.7
License-File: LICENSE
Requires-Dist: djangorestframework>=3.9
Requires-Dist: djangorestframework-filters==1.0.0.dev2
Requires-Dist: django-filter==21.1
Dynamic: license-file
